{
  "Type": "Simple",
  "Effects": {
    "CameraEffect": "ShieldCap_Big_Hit_Camera",
    "WorldSoundEventId": "SFX_ShieldCap_Hit",
    "Particles": [
      {
        "SystemId": "Shield_Bash",
        "TargetEntityPart": "PrimaryItem",
        "TargetNodeName": "Handle",
        "Scale": 0.7,
        "RotationOffset": {
          "Yaw": -180,
          "Roll": -90
        }
      }
    ],
    "ItemAnimationId": "ShieldCapRoll"
  },
  "Next": {
    "Type": "ApplyForce",
    "RunTime": 0.2,
    "Direction": {
      "Z": -2
    },
    "Force": 12,
    "AdjustVertical": false,
    "VelocityConfig": {
      "GroundResistance": 0.936,
      "GroundResistanceMax": 0.928,
      "AirResistance": 0.924,
      "AirResistanceMax": 0.932,
      "Threshold": 3,
      "Style": "Linear"
    },
    "ChangeVelocityType": "Add",
    "WaitForGround": false,
    "WaitForCollision": false,
    "Next": {
      "Type": "Simple",
      "Effects": {
        "WorldSoundEventId": "SFX_ShieldCap_Catch"
      },
      "HorizontalSpeedMultiplier": 0,
      "RunTime": 0.2
    },
    "HorizontalSpeedMultiplier": 0
  },
  "HorizontalSpeedMultiplier": 0
}
